textda/__init__.py
textda/data_expansion.py
textda/youdao_translate.py
textda/data/stopwords.txt
textda-0.1.0.6.dist-info/LICENSE
textda-0.1.0.6.dist-info/METADATA
textda-0.1.0.6.dist-info/WHEEL
textda-0.1.0.6.dist-info/top_level.txt
textda-0.1.0.6.dist-info/RECORD
