Metadata-Version: 2.1
Name: textda
Version: 0.1.0.6
Summary: this is data augmentation for chinese text
Home-page: https://github.com/wac81/textda
Author: wac
Author-email: wuanch@gmail.com
License: MIT
Keywords: classification,expansion,augmentation,addition,data,text,chinese
Platform: UNKNOWN
Classifier: Programming Language :: Python :: 3
Classifier: License :: OSI Approved :: MIT License
Classifier: Operating System :: OS Independent
Requires-Dist: jieba
Requires-Dist: synonyms
